redframes/__init__.py
redframes/checks.py
redframes/core.py
redframes/stat.py
redframes/types.py
redframes/version.py
redframes/io/__init__.py
redframes/io/convert.py
redframes/io/load.py
redframes/io/save.py
redframes/verbs/__init__.py
redframes/verbs/accumulate.py
redframes/verbs/append.py
redframes/verbs/combine.py
redframes/verbs/cross.py
redframes/verbs/dedupe.py
redframes/verbs/denix.py
redframes/verbs/drop.py
redframes/verbs/fill.py
redframes/verbs/filter.py
redframes/verbs/gather.py
redframes/verbs/group.py
redframes/verbs/join.py
redframes/verbs/mutate.py
redframes/verbs/pack.py
redframes/verbs/rank.py
redframes/verbs/rename.py
redframes/verbs/replace.py
redframes/verbs/rollup.py
redframes/verbs/sample.py
redframes/verbs/select.py
redframes/verbs/shuffle.py
redframes/verbs/sort.py
redframes/verbs/split.py
redframes/verbs/spread.py
redframes/verbs/take.py
redframes/verbs/unpack.py
tests/__init__.py
tests/test_deprecations.py
tests/test_docstrings.py
tests/test_dupe_columns.py
tests/test_index.py
tests/test_interchange.py
tests/test_io.py
tests/test_ladybugs.py
tests/test_readme.py
tests/test_side_effects.py
tests/test_type_hints.py
redframes-1.4.1.dist-info/LICENSE
redframes-1.4.1.dist-info/METADATA
redframes-1.4.1.dist-info/WHEEL
redframes-1.4.1.dist-info/top_level.txt
redframes-1.4.1.dist-info/RECORD
