Metadata-Version: 2.1
Name: redframes
Version: 1.4.1
Summary: General Purpose Data Manipulation Library
Home-page: https://github.com/maxhumber/redframes
Author: Max Humber
Author-email: max.humber@gmail.com
License: BSD 2
Classifier: Intended Audience :: Developers
Classifier: Programming Language :: Python :: 3.8
Classifier: Programming Language :: Python :: 3.9
Classifier: Programming Language :: Python :: 3.10
Classifier: Programming Language :: Python :: 3.11
Requires-Python: >=3.8
License-File: LICENSE
Requires-Dist: pandas (<3.0,>=1.5)
Provides-Extra: dev
Requires-Dist: black ; extra == 'dev'
Requires-Dist: ipykernel ; extra == 'dev'
Requires-Dist: isort ; extra == 'dev'
Requires-Dist: lxml ; extra == 'dev'
Requires-Dist: matplotlib ; extra == 'dev'
Requires-Dist: mypy ; extra == 'dev'
Requires-Dist: pandas-stubs ; extra == 'dev'
Requires-Dist: pyright ; extra == 'dev'
Requires-Dist: scikit-learn ; extra == 'dev'
Requires-Dist: tabulate ; extra == 'dev'
Provides-Extra: test
Requires-Dist: matplotlib ; extra == 'test'
Requires-Dist: scikit-learn ; extra == 'test'
